{"reposts_count": 0, "biz_feature": 4294967300, "truncated": false, "text": "#ZH16\u9876\u7ea7\u5962\u54c1\u5f00\u53d1#\u00a5450         Michael Kors \u539f\u5382\u8d27 \u975e\u5e38\u7b80\u7ea6\u79c0\u6c14\u7684\u6b3e\u5f0f \u9002\u5408\u5404\u79cd\u88c5\u626e\u548c\u5404\u4e2a\u5e74\u9f84\u5c42\u7684\u5973\u751f \u677e\u7d27\u53e3 \u7a7f\u8131\u5f88\u65b9\u4fbf \u505a\u5de5\u7cbe\u7ec6\u4e00\u7ea7\u54c1\u8d28 4.5cm\u7684\u5c0f\u65b9\u8ddf\u65e0\u7591\u62c9\u957f\u4e86\u7f8e\u817f \u539f\u5382\u9ad8\u4e1d\u5149\u7f8a\u53cd\u7ed2 \u771f\u76ae\u6cbf\u6761\u548c\u771f\u76ae\u5927\u5e95 \u5934\u5c42\u732a\u76ae\u5185\u91cc 35-39", "visible": {"type": 0, "list_id": 0}, "in_reply_to_status_id": "", "bmiddle_pic": "http://ww4.sinaimg.cn/bmiddle/005IxpdWjw1evkh2w87xpj30zk0zk41l.jpg", "original_pic": "http://ww4.sinaimg.cn/large/005IxpdWjw1evkh2w87xpj30zk0zk41l.jpg", "rid": "35_0_0_2789461601007196312", "id": 3881498736839378, "category": 31, "thumbnail_pic": "http://ww4.sinaimg.cn/thumbnail/005IxpdWjw1evkh2w87xpj30zk0zk41l.jpg", "mid": "3881498736839378", "source": "<a href=\"http://weibo.com/\" rel=\"nofollow\">\u5356\u9ad8\u4eff\u7684iPhone 6</a>", "attitudes_count": 0, "in_reply_to_screen_name": "", "in_reply_to_user_id": "", "annotations": [{"client_mblogid": "iPhone-C7098D83-4696-4346-A318-198B555863B7"}, {"mapi_request": true}], "darwin_tags": [], "favorited": false, "pic_ids": ["005IxpdWjw1evkh2w87xpj30zk0zk41l", "005IxpdWjw1evkh2wwxpyj30zk0zkjuu", "005IxpdWjw1evkh2xhtmqj30zk0zkdk5", "005IxpdWjw1evkh2y6i9kj30zk0zkae1", "005IxpdWjw1evkh2ypkjbj30zk0zkn0z", "005IxpdWjw1evkh2z8bfuj30zk0zkn07", "005IxpdWjw1evkh2zqvtdj30zk0zktc1", "005IxpdWjw1evkh30a3kgj30zk0zkado", "005IxpdWjw1evkh30tjajj30zk0zk0ws"], "source_allowclick": 0, "idstr": "3881498736839378", "source_type": 2, "user": {"verified_level": 3, "domain": "", "avatar_large": "http://tp1.sinaimg.cn/5238784732/180/5701964926/0", "bi_followers_count": 4, "verified_source": "", "ptype": 0, "ulevel": 0, "block_word": 0, "cover_image_phone": "http://ww1.sinaimg.cn/crop.0.0.0.0/005IxpdWjw1euesdyq9koj30ku0kuq6w.jpg", "star": 0, "id": 5238784732, "verified_reason_url": "", "urank": 21, "city": "1", "verified": true, "verified_contact_email": "", "verified_reason_modified": "", "credit_score": 80, "has_ability_tag": 1, "block_app": 1, "follow_me": false, "verified_reason": "\u4e2d\u56fd\u7535\u4fe1\u4e1a\u52a1\u7ecf\u7406", "followers_count": 7197, "location": "\u5e7f\u4e1c \u5e7f\u5dde", "verified_state": 0, "verified_trade": "1445", "mbtype": 13, "badge_top": "", "verified_source_url": "", "profile_url": "u/5238784732", "province": "44", "avatar_hd": "http://ww3.sinaimg.cn/crop.0.0.1136.1136.1024/005IxpdWjw8eiyrni3w6cj30vk0vktbs.jpg", "statuses_count": 19295, "description": "\u6b22\u8fce\u65b0\u8001\u5ba2\u6237\u2795\u978b\u5b50\u53f7\uff08\u4e3b\u53f7\uff09\uff1azzh1027xx  \u5305\u5305\u53f7\uff1azzh1314xx  \u4e4b\u524d\u6dd8\u5b9d\u88ab\u5c01\u5fae\u4fe1\u88ab\u5c01\u6211\u4e5f\u662f\u86ee\u9189\u7684\ud83d\udc60\ud83d\udc5b\u672c\u5e97\u4e13\u505a\u539f\u7248\u3001\u539f\u5355\u7684\ud83d\udc0d\u4f88\u54c1 \u975e\u8bda\u52ff\u6270", "friends_count": 189, "online_status": 0, "mbrank": 3, "idstr": "5238784732", "profile_image_url": "http://tp1.sinaimg.cn/5238784732/50/5701964926/0", "allow_all_act_msg": false, "verified_contact_mobile": "", "allow_all_comment": true, "geo_enabled": false, "class": 1, "name": "Lu-urygoods_ZH16", "lang": "zh-cn", "weihao": "", "extend": {"mbprivilege": "0000000000000000000000000000000000000000000000000000000000400208", "privacy": {"mobile": 1}}, "favourites_count": 0, "screen_name": "Lu-urygoods_ZH16", "url": "", "gender": "f", "created_at": "Sun Aug 03 00:38:30 +0800 2014", "verified_contact_name": "", "verified_type": 0, "following": false, "pagefriends_count": 3, "user_ability": 0}, "geo": null, "userType": 0, "created_at": "Sun Aug 30 11:21:16 +0800 2015", "mlevel": 0, "comments_count": 0, "url_objects": [{"url_ori": "ZH16\u9876\u7ea7\u5962\u54c1\u5f00\u53d1", "object": {"act_status": "00", "containerid": "100808c6eaf3c0957d156cb3c6f79c191381e8", "object": {"category": "\u65f6\u5c1a|141-\u6f6e\u4eba\u6f6e\u724c|141001", "target_url": "http://huati.weibo.com/1490167", "display_name": "ZH16\u9876\u7ea7\u5962\u54c1\u5f00\u53d1", "presenter_status": "1", "mobile": {"url": {"status": "1", "scheme": "sinaweibo://pageinfo?pageid=100808c6eaf3c0957d156cb3c6f79c191381e8&extparam=ZH16\u9876\u7ea7\u5962\u54c1\u5f00\u53d1", "name": "ZH16\u9876\u7ea7\u5962\u54c1\u5f00\u53d1"}, "page_id": "100808c6eaf3c0957d156cb3c6f79c191381e8", "card": {"status": "0"}}, "short_url": "http://t.cn/RzPavFj", "image": {"url": "http://ww1.sinaimg.cn/thumbnail/005IxpdWjw1emg8sfz2hgj30hs0hs75x.jpg"}, "object_type": "topic", "create_at": "1416158403", "summary": "V\u4fe1\uff1azzh1027xx \u4e00\u624b\u8d27\u6e90\uff01\u505a\u751f\u610f\u5982\u505a\u4eba\uff01\u6240\u6709\u7684\u4e1c\u897f\u4e00\u5f8b\u4e0d\u8bae\u4ef7\uff01\u770b\u4e00\u4e0b\u6211\u7684\u7f6e\u9876\u5fae\u535a\uff5e\u5bf9\u53f7\u5165\u5ea7\ud83d\ude0b", "url": "http://huati.weibo.com/1490167", "biz": {"containerid": "100808c6eaf3c0957d156cb3c6f79c191381e8", "biz_id": "100808"}, "location": "44-1", "attribute": "1", "tid": "1490167", "topic_tag": "\u5962\u4f88\u54c1\u590d\u523b,\u4e13\u67dc\u6709\u7684\u6211\u90fd\u6709,\u7537\u88c5\u5973\u88c5\u00b7\u9970\u54c1,\u978b\u00b7\u5305\u5305\u00b7\u56f4\u5dfe", "id": "1022:100808c6eaf3c0957d156cb3c6f79c191381e8"}, "timestamp": 1445876371278, "object_type": "topic", "object_domain_id": "1022", "uuid": 3777704468972197, "object_id": "1022:100808c6eaf3c0957d156cb3c6f79c191381e8", "safe_status": 1, "last_modified": "Tue Oct 27 00:19:31 CST 2015", "activate_status": "0", "show_status": "10"}, "object_id": "1022:100808c6eaf3c0957d156cb3c6f79c191381e8", "card_info_un_integrity": false, "like_count": 315, "asso_like_count": 0, "follower_count": 262}]}