{"reposts_count": 0, "biz_feature": 4294967300, "truncated": false, "text": "#michael kors#\u6253\u6298\u5566", "visible": {"type": 0, "list_id": 0}, "in_reply_to_status_id": "", "relation": null, "bmiddle_pic": "http://ww4.sinaimg.cn/bmiddle/8efd6d3bgw1evltkqv4vrj20hs0nqq4j.jpg", "original_pic": "http://ww4.sinaimg.cn/large/8efd6d3bgw1evltkqv4vrj20hs0nqq4j.jpg", "rid": "15_0_0_2669619291735279823", "id": 3881920993865164, "category": 31, "thumbnail_pic": "http://ww4.sinaimg.cn/thumbnail/8efd6d3bgw1evltkqv4vrj20hs0nqq4j.jpg", "mid": "3881920993865164", "source": "<a href=\"http://app.weibo.com/t/feed/9ksdit\" rel=\"nofollow\">iPhone\u5ba2\u6237\u7aef</a>", "attitudes_count": 0, "in_reply_to_screen_name": "", "in_reply_to_user_id": "", "base62_id": "Cyn8Dgdvm", "annotations": [{"client_mblogid": "iPhone-2938DDFD-196E-4E9A-A3F2-805E253CB9B2"}, {"mapi_request": true}], "darwin_tags": [], "favorited": false, "pic_ids": ["8efd6d3bgw1evltkqv4vrj20hs0nqq4j", "8efd6d3bgw1evltkrdlhmj20hs0nqq4g", "8efd6d3bgw1evltkrtpr7j20hs0nqt9y", "8efd6d3bgw1evltksu1byj20hs0nqmzh", "8efd6d3bgw1evltktfg3kj20hs0nqwj5", "8efd6d3bgw1evltkqaasfj20hs0nq40v", "8efd6d3bgw1evltku5r5lj20hs0nqadu", "8efd6d3bgw1evltkuovltj20hs0nqwhw"], "source_allowclick": 0, "idstr": "3881920993865164", "source_type": 1, "user": {"bi_followers_count": 4, "domain": "", "avatar_large": "http://tp4.sinaimg.cn/2398973243/180/5735919383/0", "verified_source": "", "ptype": 0, "ulevel": 0, "block_word": 0, "star": 0, "id": 2398973243, "verified_reason_url": "", "urank": 7, "city": "1", "verified": false, "extend": {"mbprivilege": "0000000000000000000000000000000000000000000000000000000000000000", "privacy": {"mobile": 1}}, "credit_score": 80, "has_ability_tag": 0, "block_app": 0, "follow_me": false, "verified_reason": "", "followers_count": 23, "location": "\u5b89\u5fbd \u5408\u80a5", "badge_top": "", "verified_trade": "", "mbtype": 0, "type": 1, "verified_source_url": "", "profile_url": "u/2398973243", "province": "34", "avatar_hd": "http://ww2.sinaimg.cn/crop.0.0.640.640.1024/8efd6d3bjw8evl3tqmc87j20hs0hs3zl.jpg", "statuses_count": 94, "description": "mk\uff0cks\uff0ccoach\uff0cmcm\u6700\u65b0\u6b3e\u5206\u4eab\uff01\u559c\u6b22\u7684\u53ef\u4ee5m\u6211wei xin\uff1abbdaigou68", "friends_count": 59, "online_status": 0, "mbrank": 0, "idstr": "2398973243", "profile_image_url": "http://tp4.sinaimg.cn/2398973243/50/5735919383/0", "allow_all_act_msg": false, "badge": {"bind_taobao": 0, "hongbao_2014": 0, "gongyi_level": 0, "dailv": 0, "gongyi": 0, "travel2013": 0, "anniversary": 0, "shuang11_2015": 0, "taobao": 0, "uc_domain": 0, "enterprise": 0, "suishoupai_2014": 0, "zongyiji": 0}, "allow_all_comment": true, "geo_enabled": true, "class": 1, "name": "mk\u5305\u5305\u4ee3\u8d2d", "lang": "zh-cn", "weihao": "", "remark": "", "favourites_count": 1, "screen_name": "mk\u5305\u5305\u4ee3\u8d2d", "level": 1, "url": "", "gender": "f", "created_at": "Sun Apr 07 22:21:18 +0800 2013", "verified_type": -1, "following": false, "pagefriends_count": 8, "user_ability": 0}, "geo": null, "status": 0, "userType": 0, "created_at": "Mon Aug 31 15:19:10 +0800 2015", "mlevel": 0, "comments_count": 0, "url_objects": [{"url_ori": "michael kors", "object": {"act_status": "00", "containerid": "10080824d65c4766a9b5a5092e5bb75b056f0d", "object": {"target_url": "http://weibo.cn/p/10080824d65c4766a9b5a5092e5bb75b056f0d", "display_name": "michael kors", "mobile": {"url": {"status": "1", "scheme": "sinaweibo://pageinfo?pageid=10080824d65c4766a9b5a5092e5bb75b056f0d&extparam=michael+kors", "name": "michael kors"}, "page_id": "10080824d65c4766a9b5a5092e5bb75b056f0d", "card": {"status": "0", "scheme": "sinaweibo://pageinfo?pageid=10080824d65c4766a9b5a5092e5bb75b056f0d&extparam=michael+kors", "pic": "http://u1.sinaimg.cn/upload/2012/12/28/ht_page_icon.png", "contents": ["#michael kors#"]}}, "short_url": "http://t.cn/zQJdTrg", "image": {"url": "", "width": "", "height": ""}, "object_type": "topic", "summary": "", "url": "http://weibo.cn/p/10080824d65c4766a9b5a5092e5bb75b056f0d", "biz": {"containerid": "10080824d65c4766a9b5a5092e5bb75b056f0d", "biz_id": "100808"}, "id": "1022:10080824d65c4766a9b5a5092e5bb75b056f0d"}, "timestamp": 1446076202433, "object_type": "topic", "object_domain_id": "1022", "uuid": 3605492646590035, "object_id": "1022:10080824d65c4766a9b5a5092e5bb75b056f0d", "safe_status": 1, "last_modified": "Mon Jul 29 20:11:35 CST 2013", "activate_status": "0", "show_status": "10"}, "object_id": "1022:10080824d65c4766a9b5a5092e5bb75b056f0d", "card_info_un_integrity": false, "like_count": 183, "asso_like_count": 0, "follower_count": 99}]}