{"reposts_count": 0, "biz_feature": 4294967300, "truncated": false, "text": "\u4eca\u5929\u6700\u5927\u7684\u767d\u83dc\u6765\u4e86\uff01\u4e70\u5230\u6211\u90fd\u6fc0\u52a8\u4e86\u534a\u5929kate spade\u85cf\u84dd\u8272\u5168\u7f8a\u6bdb\u53cc\u6263oversize\u5927\u8863\u4eca\u5e74\u5f88\u6d41\u884c\u7684\u6b3eM\u4e00\u4ef6\u5f88\u559c\u6b22\u8fd9\u4e2a\u9886\u5b50\u6211\u8116\u5b50\u4e0d\u957f\uff0c\u8fd9\u4e2a\u9886\u5f88\u5408\u9002\u5168\u7f8a\u6bdb\u597d\u6696\u548c\uff01\u5173\u952e\u8fd9\u4e2a\u5f62\u7279\u522b\u7684\u5e05\u6c14\u4e0d\u662f\u6536\u8170\u6b3e\uff0c\u662f\u6709\u70b9\u5a03\u5a03\u886b\u526a\u88c1\u8ddf\u6211\u5c3a\u5bf8\u4e00\u6837\u6216\u8005\u7a0d\u5fae\u80d6\u70b9\u7684\u90fd\u53ef\u4ee5\u6298\u6263\u4ef7\u5c31\u662f680\u5200\uff08\u8fd8\u4e0d\u7b97\u6d88\u8d39\u7a0e\u548c\u90ae\u8d39\uff09\u4ffa\u4eec\u7684\u767d\u83dc\u4ef72800", "filterID": "0:1,1:1,2:1,3:1,4:1,5:1,6:1,7:1,8:1", "visible": {"type": 0, "list_id": 0}, "in_reply_to_status_id": "", "relation": null, "bmiddle_pic": "http://ww2.sinaimg.cn/bmiddle/7210e351gw1evx85wnwubj20qo0zkdii.jpg", "original_pic": "http://ww2.sinaimg.cn/large/7210e351gw1evx85wnwubj20qo0zkdii.jpg", "rid": "25_0_0_2666494960708461912", "id": 3885496038545730, "category": 31, "thumbnail_pic": "http://ww2.sinaimg.cn/thumbnail/7210e351gw1evx85wnwubj20qo0zkdii.jpg", "mid": "3885496038545730", "source": "<a href=\"http://app.weibo.com/t/feed/1J95c3\" rel=\"nofollow\">\u7ea2\u7c73\u624b\u673a</a>", "attitudes_count": 1, "in_reply_to_screen_name": "", "in_reply_to_user_id": "", "base62_id": "CzS8PzR8m", "annotations": [{"client_mblogid": "de3c8caa-9da3-4e75-99af-5459bfe62f7b"}, {"mapi_request": true}], "darwin_tags": [], "favorited": false, "pic_ids": ["7210e351gw1evx85wnwubj20qo0zkdii", "7210e351gw1evx85x3ocgj20qo0zkgoe", "7210e351gw1evx85xkqc6j20qo0zkq5o", "7210e351gw1evx85y3hcaj20qo0zkmze", "7210e351gw1evx85ymln6j20qo0zkwgq", "7210e351gw1evx85zjlf9j20qo0zk45e", "7210e351gw1evx8603tm7j20sg0zkn11", "7210e351gw1evx860n63oj20810rsab8", "7210e351gw1evx86193drj20qo0zk78n"], "source_allowclick": 0, "stickerID": "0:-1,1:-1,2:-1,3:-1,4:-1,5:-1,6:-1,7:-1,8:-1", "idstr": "3885496038545730", "source_type": 1, "user": {"bi_followers_count": 108, "domain": "", "avatar_large": "http://tp2.sinaimg.cn/1913709393/180/5730959601/0", "verified_source": "", "ptype": 0, "ulevel": 0, "block_word": 0, "cover_image_phone": "http://ww2.sinaimg.cn/crop.0.0.640.640.640/a1d3feabjw1ecasunmkncj20hs0hsq4j.jpg", "star": 0, "id": 1913709393, "verified_reason_url": "", "urank": 30, "city": "1", "verified": false, "extend": {"mbprivilege": "0000000000000000000000000000000000000000000000000000000000400208", "privacy": {"mobile": 1}}, "credit_score": 80, "has_ability_tag": 1, "block_app": 1, "follow_me": false, "verified_reason": "", "followers_count": 5921, "location": "\u6d77\u5916 \u7f8e\u56fd", "badge_top": "", "verified_trade": "", "mbtype": 12, "type": 1, "verified_source_url": "", "profile_url": "u/1913709393", "province": "400", "avatar_hd": "http://ww4.sinaimg.cn/crop.0.0.757.757.1024/7210e351jw8etqqnioe0uj20l10l2jse.jpg", "statuses_count": 9630, "description": "\u6d0b\u7801\u5934\u5e97\uff1ahttp://www.ymatou.com/Shop/276133", "friends_count": 196, "online_status": 0, "mbrank": 5, "idstr": "1913709393", "profile_image_url": "http://tp2.sinaimg.cn/1913709393/50/5730959601/0", "allow_all_act_msg": true, "following": false, "badge": {"bind_taobao": 0, "hongbao_2014": 0, "gongyi_level": 0, "dailv": 0, "gongyi": 0, "travel2013": 0, "anniversary": 0, "shuang11_2015": 0, "taobao": 0, "uc_domain": 0, "enterprise": 0, "suishoupai_2014": 0, "zongyiji": 0}, "allow_all_comment": true, "geo_enabled": true, "class": 1, "name": "Leo\u5b9d\u8d1d\u5988\u5728\u7f8e\u56fd", "lang": "zh-cn", "weihao": "", "remark": "", "favourites_count": 39, "screen_name": "Leo\u5b9d\u8d1d\u5988\u5728\u7f8e\u56fd", "level": 1, "url": "http://blog.sina.com.cn/u/1913709393", "gender": "f", "created_at": "Thu Jan 06 23:11:04 +0800 2011", "verified_type": -1, "cover_image": "http://ww3.sinaimg.cn/crop.0.176.980.300/7210e351gw1ece3jfoko8j20r80i4jw2.jpg", "pagefriends_count": 0, "user_ability": 0}, "geo": null, "status": 0, "userType": 0, "created_at": "Thu Sep 10 12:05:07 +0800 2015", "mlevel": 0, "comments_count": 3, "url_objects": []}