{"reposts_count": 5, "biz_feature": 4294967300, "truncated": false, "text": "Grazia China x Michael Kors Met Gala 2015: Natasha Poly / Karen Elson / Linda Evangelista / Caroline Trentini / Constance Jablonski / Lily Donaldson / Rosie Huntington-Whiteley / Anna Wintour / Anna Ewers / Sasha Pivovarova. \u7b2c\u4e00\u90e8\u5206", "visible": {"type": 0, "list_id": 0}, "in_reply_to_status_id": "", "relation": null, "bmiddle_pic": "http://ww4.sinaimg.cn/bmiddle/005Q8YEngw1ewxlusqz2nj30ff0kg0ud.jpg", "original_pic": "http://ww4.sinaimg.cn/large/005Q8YEngw1ewxlusqz2nj30ff0kg0ud.jpg", "rid": "34_0_0_2666481757982320750", "id": 3896901252255890, "category": 31, "thumbnail_pic": "http://ww4.sinaimg.cn/thumbnail/005Q8YEngw1ewxlusqz2nj30ff0kg0ud.jpg", "mid": "3896901252255890", "source": "<a href=\"http://weibo.com/\" rel=\"nofollow\">Android</a>", "attitudes_count": 8, "in_reply_to_screen_name": "", "in_reply_to_user_id": "", "base62_id": "CEEQl9sRk", "annotations": [{"client_mblogid": "59f657c1-7ef1-47e0-a4a1-c7c0c2649b12"}, {"mapi_request": true}], "darwin_tags": [], "favorited": false, "pic_ids": ["005Q8YEngw1ewxlusqz2nj30ff0kg0ud", "005Q8YEngw1ewxlutf2n4j30m80et40q", "005Q8YEngw1ewxluufw8cj30iz0r0ae4", "005Q8YEngw1ewxlxhkxcuj30co0hsdhz", "005Q8YEngw1ewxluw3g3qj30iz0r277d", "005Q8YEngw1ewxlv1magpj30ei0lq768", "005Q8YEngw1ewxlv1xcklj30m80et3zp", "005Q8YEngw1ewxlv2jcfcj30m80etdi4", "005Q8YEngw1ewxlv309b0j30m80etmza"], "source_allowclick": 0, "idstr": "3896901252255890", "source_type": 2, "user": {"bi_followers_count": 83, "domain": "", "avatar_large": "http://tp4.sinaimg.cn/5351173399/180/5740721314/0", "verified_source": "", "ptype": 0, "ulevel": 0, "block_word": 0, "cover_image_phone": "http://ww4.sinaimg.cn/crop.0.0.640.640.640/a1d3feabjw1ecat3p2p2qj20hs0hsmz4.jpg", "star": 0, "id": 5351173399, "verified_reason_url": "", "urank": 17, "city": "1000", "verified": false, "extend": {"mbprivilege": "0000000000000000000000000000000000000000000000000000000000000000", "privacy": {"mobile": 0}}, "credit_score": 80, "has_ability_tag": 1, "block_app": 0, "follow_me": false, "verified_reason": "", "followers_count": 1900, "location": "\u5176\u4ed6", "badge_top": "", "verified_trade": "", "mbtype": 0, "type": 1, "verified_source_url": "", "profile_url": "u/5351173399", "province": "100", "avatar_hd": "http://ww3.sinaimg.cn/crop.0.0.480.480.1024/005Q8YEnjw8exdcyjw6ftj30dc0dcgm7.jpg", "statuses_count": 665, "description": "\u3010VOGUE\u6536\u85cf\u9986\u3011\u3016\u5173\u4e8e\u6fb3\u5927\u5229\u4e9a\u5a03\u5a03\u8138\u8d85\u6a21Gemma Ward\u7684\u4e00\u5207\u3017\u6b22\u8fce\u5173\u6ce8.", "friends_count": 138, "online_status": 0, "mbrank": 0, "idstr": "5351173399", "profile_image_url": "http://tp4.sinaimg.cn/5351173399/50/5740721314/0", "allow_all_act_msg": false, "badge": {"bind_taobao": 0, "hongbao_2014": 0, "gongyi_level": 0, "dailv": 0, "gongyi": 0, "travel2013": 0, "anniversary": 0, "shuang11_2015": 0, "taobao": 0, "uc_domain": 0, "enterprise": 0, "suishoupai_2014": 0, "zongyiji": 0}, "allow_all_comment": true, "geo_enabled": false, "class": 1, "name": "-GemmaWardFans", "lang": "zh-cn", "weihao": "", "remark": "", "favourites_count": 69, "screen_name": "-GemmaWardFans", "level": 1, "url": "", "gender": "f", "created_at": "Thu Oct 30 23:12:10 +0800 2014", "verified_type": -1, "following": false, "pagefriends_count": 1, "user_ability": 0}, "geo": null, "status": 0, "userType": 0, "created_at": "Sun Oct 11 23:25:22 +0800 2015", "mlevel": 0, "comments_count": 0, "url_objects": []}