{"status": {"reposts_count": 0, "biz_feature": 4294967300, "truncated": false, "text": "Throw back Michael Kors S/S 16", "visible": {"type": 0, "list_id": 0}, "in_reply_to_status_id": "", "bmiddle_pic": "http://ww1.sinaimg.cn/bmiddle/98d54454jw1ewdjp123uyj20b40gogn6.jpg", "original_pic": "http://ww1.sinaimg.cn/large/98d54454jw1ewdjp123uyj20b40gogn6.jpg", "id": 3890611788726141, "thumbnail_pic": "http://ww1.sinaimg.cn/thumbnail/98d54454jw1ewdjp123uyj20b40gogn6.jpg", "mid": "3890611788726141", "source": "<a href=\"http://app.weibo.com/t/feed/5yiHuw\" rel=\"nofollow\">iPhone 6 Plus</a>", "attitudes_count": 0, "in_reply_to_screen_name": "", "in_reply_to_user_id": "", "annotations": [{"client_mblogid": "iPhone-67A8AAF7-8F8C-49D1-89F6-25DAC75F5672"}, {"mapi_request": true}], "darwin_tags": [], "favorited": false, "pic_ids": ["98d54454jw1ewdjp123uyj20b40gogn6"], "source_allowclick": 0, "idstr": "3890611788726141", "source_type": 1, "user": {"bi_followers_count": 9, "domain": "", "avatar_large": "http://tp1.sinaimg.cn/2564113492/180/5739875043/0", "verified_source": "", "ptype": 0, "ulevel": 0, "block_word": 0, "cover_image_phone": "http://ww2.sinaimg.cn/crop.0.0.640.640.640/a1d3feabjw1ecasunmkncj20hs0hsq4j.jpg", "star": 0, "id": 2564113492, "verified_reason_url": "", "urank": 9, "city": "3", "verified": false, "extend": {"mbprivilege": "0000000000000000000000000000000000000000000000000000000000000000", "privacy": {"mobile": 1}}, "credit_score": 80, "has_ability_tag": 1, "block_app": 0, "follow_me": false, "verified_reason": "", "followers_count": 6083, "location": "\u6d77\u5916 \u6cd5\u56fd", "badge_top": "", "verified_trade": "", "mbtype": 0, "type": 1, "verified_source_url": "", "profile_url": "u/2564113492", "province": "400", "avatar_hd": "http://ww4.sinaimg.cn/crop.1.0.1239.1239.1024/98d54454jw8ex21ax195ej20yi0yf42b.jpg", "statuses_count": 36, "description": "17\u5c81 - Elite Paris - Instagram : chen_estelle", "friends_count": 23, "online_status": 0, "mbrank": 0, "idstr": "2564113492", "profile_image_url": "http://tp1.sinaimg.cn/2564113492/50/5739875043/0", "allow_all_act_msg": false, "badge": {"bind_taobao": 0, "hongbao_2014": 0, "gongyi_level": 0, "dailv": 0, "gongyi": 0, "travel2013": 0, "anniversary": 0, "shuang11_2015": 0, "taobao": 0, "uc_domain": 0, "enterprise": 0, "suishoupai_2014": 0, "zongyiji": 0}, "allow_all_comment": true, "geo_enabled": true, "class": 1, "name": "chenestelle", "lang": "zh-cn", "weihao": "", "remark": "", "favourites_count": 0, "screen_name": "chenestelle", "level": 1, "url": "", "gender": "f", "created_at": "Sun Nov 27 01:37:05 +0800 2011", "verified_type": -1, "following": false, "pagefriends_count": 0, "user_ability": 0}, "geo": null, "userType": 0, "created_at": "Thu Sep 24 14:53:16 +0800 2015", "mlevel": 0, "comments_count": 0}, "source_allowclick": 0, "source_type": 2, "text": "\u6f02\u4eae\u2026\u2026\uff08\u9664\u4e86\u6f02\u4eae\u6211\u8fd8\u80fd\u8bf4\u4e9b\u4ec0\u4e48\u7684\u4f60\u8fde\u6587\u5b57\u90fd\u4e0d\u914d[\u8870]\uff09", "created_at": "Thu Sep 24 16:26:35 +0800 2015", "mid": "3890635277028125", "idstr": "3890635277028125", "source": "<a href=\"http://weibo.com/\" rel=\"nofollow\">\u5e73\u884c\u4e16\u754c/.Android</a>", "user": {"bi_followers_count": 6, "domain": "", "avatar_large": "http://tp3.sinaimg.cn/5494267506/180/5734406891/0", "cardid": "star_001", "verified_source": "", "ptype": 0, "ulevel": 0, "block_word": 0, "cover_image_phone": "http://ww3.sinaimg.cn/crop.0.0.0.0/005ZPnXQjw1ew294ipgjzj30u00u0q7a.jpg", "star": 0, "id": 5494267506, "verified_reason_url": "", "urank": 14, "city": "1", "verified": false, "extend": {"mbprivilege": "0000000000000000000000000000000000000000000000000000000000c00208", "privacy": {"mobile": 1}}, "credit_score": 80, "has_ability_tag": 0, "block_app": 1, "follow_me": false, "verified_reason": "", "followers_count": 292, "location": "\u5409\u6797 \u957f\u6625", "badge_top": "", "verified_trade": "", "mbtype": 12, "type": 1, "verified_source_url": "", "profile_url": "u/5494267506", "province": "22", "avatar_hd": "http://ww2.sinaimg.cn/crop.0.0.1080.1080.1024/005ZPnXQjw8ev0v8soloqj30u00u0ac5.jpg", "statuses_count": 182, "description": "B e i n g   t o w a r d s   d e a t h . /", "friends_count": 102, "online_status": 0, "mbrank": 2, "idstr": "5494267506", "profile_image_url": "http://tp3.sinaimg.cn/5494267506/50/5734406891/0", "allow_all_act_msg": false, "badge": {"bind_taobao": 1, "hongbao_2014": 0, "gongyi_level": 0, "dailv": 0, "gongyi": 0, "travel2013": 0, "anniversary": 0, "shuang11_2015": 0, "taobao": 0, "uc_domain": 0, "enterprise": 0, "suishoupai_2014": 0, "zongyiji": 0}, "allow_all_comment": true, "geo_enabled": true, "class": 1, "name": "\u5b8b\u90c1Z", "lang": "zh-cn", "weihao": "", "remark": "", "favourites_count": 8, "screen_name": "\u5b8b\u90c1Z", "level": 1, "url": "", "gender": "f", "created_at": "Sun Jan 25 09:12:14 +0800 2015", "verified_type": -1, "following": false, "pagefriends_count": 0, "user_ability": 0}, "id": 3890635277028125, "floor_num": 13}