{"reposts_count": 0, "biz_feature": 4294967300, "truncated": false, "text": "\u7f8e\u56fd\u76f4\u90ae kate spade \u4e24\u7528\u8033\u6735\u5305 6\u6298 \u5305\u90ae\u5230\u5bb6 2000RMB", "visible": {"type": 0, "list_id": 0}, "in_reply_to_status_id": "", "relation": null, "bmiddle_pic": "http://ww4.sinaimg.cn/bmiddle/005P87SKjw1evumyd0bosj30ku112tcl.jpg", "original_pic": "http://ww4.sinaimg.cn/large/005P87SKjw1evumyd0bosj30ku112tcl.jpg", "rid": "3_0_0_2789509111905189960", "id": 3884684687632870, "category": 31, "thumbnail_pic": "http://ww4.sinaimg.cn/thumbnail/005P87SKjw1evumyd0bosj30ku112tcl.jpg", "mid": "3884684687632870", "source": "<a href=\"http://app.weibo.com/t/feed/3o33sO\" rel=\"nofollow\">iPhone 6</a>", "attitudes_count": 0, "in_reply_to_screen_name": "", "in_reply_to_user_id": "", "base62_id": "Czx2cw1EO", "annotations": [{"client_mblogid": "iPhone-469E3E23-7E1C-4FD3-B973-109DE53771BF"}, {"mapi_request": true}], "darwin_tags": [], "favorited": false, "pic_ids": ["005P87SKjw1evumyd0bosj30ku112tcl", "005P87SKjw1evumy9r0j8j30ku112n7w", "005P87SKjw1evumyob2thj30ku1124ak", "005P87SKjw1evumz1ahsrj30ku112gyg", "005P87SKjw1evumzf7yqyj30ku112q9x"], "source_allowclick": 0, "idstr": "3884684687632870", "source_type": 1, "user": {"bi_followers_count": 23, "domain": "", "avatar_large": "http://tp3.sinaimg.cn/5336194222/180/5717036513/0", "verified_source": "", "ptype": 0, "ulevel": 0, "block_word": 0, "cover_image_phone": "http://ww2.sinaimg.cn/crop.0.0.640.640.640/a1d3feabjw1ecasunmkncj20hs0hsq4j.jpg", "star": 0, "id": 5336194222, "verified_reason_url": "", "urank": 13, "city": "1", "verified": false, "extend": {"mbprivilege": "0000000000000000000000000000000000000000000000000000000000000000", "privacy": {"mobile": 1}}, "credit_score": 80, "has_ability_tag": 0, "block_app": 0, "follow_me": false, "verified_reason": "", "followers_count": 50, "location": "\u6d77\u5916 \u7f8e\u56fd", "badge_top": "", "verified_trade": "", "mbtype": 0, "type": 1, "verified_source_url": "", "profile_url": "u/5336194222", "province": "400", "avatar_hd": "http://ww3.sinaimg.cn/crop.0.0.750.750.1024/005P87SKjw8eokfrvrk9qj30ku0kut9b.jpg", "statuses_count": 167, "description": "\u5916\u9762\u98ce\u96e8\u7433\u7405 \u6f2b\u5c71\u904d\u91ce\u90fd\u662f\u4eca\u5929", "friends_count": 24, "online_status": 0, "mbrank": 0, "idstr": "5336194222", "profile_image_url": "http://tp3.sinaimg.cn/5336194222/50/5717036513/0", "allow_all_act_msg": false, "badge": {"bind_taobao": 0, "hongbao_2014": 0, "gongyi_level": 0, "dailv": 0, "gongyi": 0, "travel2013": 0, "anniversary": 0, "shuang11_2015": 0, "taobao": 0, "uc_domain": 0, "enterprise": 0, "suishoupai_2014": 0, "zongyiji": 0}, "allow_all_comment": true, "geo_enabled": true, "class": 1, "name": "\u5f2f\u9c7c\u897f", "lang": "zh-cn", "weihao": "", "remark": "", "favourites_count": 0, "screen_name": "\u5f2f\u9c7c\u897f", "level": 1, "url": "", "gender": "f", "created_at": "Mon Oct 20 11:29:27 +0800 2014", "verified_type": -1, "following": false, "pagefriends_count": 0, "user_ability": 0}, "geo": null, "status": 0, "userType": 0, "created_at": "Tue Sep 08 06:21:06 +0800 2015", "mlevel": 0, "comments_count": 0, "url_objects": []}