{"reposts_count": 0, "biz_feature": 4294967300, "truncated": false, "text": "kate spade\u8d1d\u58f3\u5305\u5c31\u8fd9\u4e00\u4e2a\u53f7 \u6b64\u82721480\u76f4\u90ae[\u9f13\u638c]", "visible": {"type": 0, "list_id": 0}, "in_reply_to_status_id": "", "relation": null, "bmiddle_pic": "http://ww2.sinaimg.cn/bmiddle/3cc180b9gw1evsritft2ij20ct0dbjro.jpg", "original_pic": "http://ww2.sinaimg.cn/large/3cc180b9gw1evsritft2ij20ct0dbjro.jpg", "rid": "19_0_0_2789509111905193708", "id": 3884097317079432, "category": 31, "thumbnail_pic": "http://ww2.sinaimg.cn/thumbnail/3cc180b9gw1evsritft2ij20ct0dbjro.jpg", "mid": "3884097317079432", "source": "<a href=\"http://app.weibo.com/t/feed/3o33sO\" rel=\"nofollow\">iPhone 6</a>", "attitudes_count": 0, "in_reply_to_screen_name": "", "in_reply_to_user_id": "", "base62_id": "CzhKPtHGo", "annotations": [{"client_mblogid": "iPhone-D89E7C0C-71EE-43FD-B6E9-438A44BC88EA"}, {"mapi_request": true}], "darwin_tags": [], "favorited": false, "pic_ids": ["3cc180b9gw1evsritft2ij20ct0dbjro", "3cc180b9gw1evsritsibuj20e60f5mz6", "3cc180b9gw1evsrisy756j20e20f7761", "3cc180b9gw1evsriu5jthj20cj0gaq42"], "source_allowclick": 0, "idstr": "3884097317079432", "source_type": 1, "user": {"bi_followers_count": 1, "domain": "", "avatar_large": "http://tp2.sinaimg.cn/1019314361/180/5737186542/0", "verified_source": "", "ptype": 0, "ulevel": 36028797018963968, "block_word": 0, "cover_image_phone": "http://ww3.sinaimg.cn/crop.0.0.640.640.640/a1d3feabjw1eca1ktsx9tj20hs0hsjtk.jpg", "star": 0, "id": 1019314361, "verified_reason_url": "", "urank": 4, "city": "1", "verified": false, "extend": {"mbprivilege": "0000000000000000000000000000000000000000000000000000000000000000", "privacy": {"mobile": 1}}, "credit_score": 80, "has_ability_tag": 0, "block_app": 0, "follow_me": false, "verified_reason": "", "followers_count": 51, "location": "\u6d77\u5916 \u7f8e\u56fd", "badge_top": "", "verified_trade": "", "mbtype": 0, "type": 1, "verified_source_url": "", "profile_url": "u/1019314361", "province": "400", "avatar_hd": "http://ww4.sinaimg.cn/crop.0.0.511.511.1024/3cc180b9jw8ew22878htfj20e70e8aah.jpg", "statuses_count": 183, "description": "\u5fae\u4fe1\uff1aSylvia1987", "friends_count": 29, "online_status": 0, "mbrank": 0, "idstr": "1019314361", "profile_image_url": "http://tp2.sinaimg.cn/1019314361/50/5737186542/0", "allow_all_act_msg": false, "badge": {"bind_taobao": 0, "hongbao_2014": 0, "gongyi_level": 0, "dailv": 0, "gongyi": 0, "travel2013": 0, "anniversary": 0, "shuang11_2015": 0, "taobao": 0, "uc_domain": 0, "enterprise": 0, "suishoupai_2014": 0, "zongyiji": 0}, "allow_all_comment": true, "geo_enabled": true, "class": 1, "name": "\u6587\u5b50\u7f8e\u56fd\u8d2dgogo", "lang": "zh-cn", "weihao": "", "remark": "", "favourites_count": 0, "screen_name": "\u6587\u5b50\u7f8e\u56fd\u8d2dgogo", "level": 1, "url": "", "gender": "f", "created_at": "Sat Mar 01 01:48:21 +0800 2014", "verified_type": -1, "following": false, "pagefriends_count": 0, "user_ability": 0}, "geo": null, "status": 0, "userType": 0, "created_at": "Sun Sep 06 15:27:06 +0800 2015", "mlevel": 0, "comments_count": 0, "url_objects": []}