{"reposts_count": 0, "biz_feature": 4294967298, "truncated": false, "text": "#Kate spade# \u4e2d\u53f7\u8d1d\u58f3\u5305\uff0c\u751c\u6a59\u8272\u597d\u4ef7\u683c\uff0c950\u5230\u624b\u5662\u3002", "visible": {"type": 0, "list_id": 0}, "in_reply_to_status_id": "", "relation": null, "bmiddle_pic": "http://ww3.sinaimg.cn/bmiddle/62dcdb2djw1evqmm8uz5hj20oc0l5wga.jpg", "original_pic": "http://ww3.sinaimg.cn/large/62dcdb2djw1evqmm8uz5hj20oc0l5wga.jpg", "rid": "22_0_0_2789457572297137144", "id": 3883427718109721, "category": 31, "thumbnail_pic": "http://ww3.sinaimg.cn/thumbnail/62dcdb2djw1evqmm8uz5hj20oc0l5wga.jpg", "mid": "3883427718109721", "source": "<a href=\"http://app.weibo.com/t/feed/1oul9z\" rel=\"nofollow\">iPad mini</a>", "attitudes_count": 0, "in_reply_to_screen_name": "", "in_reply_to_user_id": "", "base62_id": "Cz0kPy1HX", "annotations": [{"client_mblogid": "iPhone-CA41E992-A466-4A0C-98D9-B36FA80EC7E5", "shooting": 1}, {"mapi_request": true}], "darwin_tags": [], "favorited": false, "pic_ids": ["62dcdb2djw1evqmm8uz5hj20oc0l5wga", "62dcdb2djw1evqmmawqtlj20p50y0wi6", "62dcdb2djw1evqmmdf73nj20p50xdtaq", "62dcdb2djw1evqmmgja7kj20om0weaex"], "source_allowclick": 0, "idstr": "3883427718109721", "source_type": 1, "user": {"bi_followers_count": 35, "domain": "loveffw", "avatar_large": "http://tp2.sinaimg.cn/1658641197/180/5715143356/0", "verified_source": "", "ptype": 0, "ulevel": 36028797018963968, "block_word": 0, "star": 0, "id": 1658641197, "verified_reason_url": "", "urank": 16, "city": "1000", "verified": false, "extend": {"mbprivilege": "0000000000000000000000000000000000000000000000000000000000400208", "privacy": {"mobile": 1}}, "credit_score": 80, "has_ability_tag": 0, "block_app": 1, "follow_me": false, "verified_reason": "", "followers_count": 377, "location": "\u5176\u4ed6", "badge_top": "", "verified_trade": "", "mbtype": 13, "type": 1, "verified_source_url": "", "profile_url": "loveffw", "province": "100", "avatar_hd": "http://ww3.sinaimg.cn/crop.0.0.640.640.1024/62dcdb2djw8env3tn0q1cj20hs0hsgm2.jpg", "statuses_count": 1775, "description": "\u6dd8\u5b9d\u5e97\u94fa\u540d\uff1a\u80a5\u80a5\u8587\u5168\u7403\u8d2d \u5fae\u4fe1\uff1agugujiang520", "friends_count": 171, "online_status": 0, "mbrank": 3, "idstr": "1658641197", "profile_image_url": "http://tp2.sinaimg.cn/1658641197/50/5715143356/0", "allow_all_act_msg": false, "badge": {"bind_taobao": 1, "hongbao_2014": 0, "gongyi_level": 0, "dailv": 0, "gongyi": 0, "travel2013": 0, "anniversary": 0, "shuang11_2015": 0, "taobao": 1, "uc_domain": 0, "enterprise": 0, "suishoupai_2014": 0, "zongyiji": 0}, "allow_all_comment": true, "geo_enabled": true, "class": 1, "name": "\u80a5\u80a5\u80a5\u80a5\u8587\u5168\u7403\u8d2d", "lang": "zh-cn", "weihao": "", "remark": "", "favourites_count": 29, "screen_name": "\u80a5\u80a5\u80a5\u80a5\u8587\u5168\u7403\u8d2d", "level": 1, "url": "", "gender": "f", "created_at": "Fri Jan 02 13:16:51 +0800 2015", "verified_type": -1, "following": false, "pagefriends_count": 0, "user_ability": 0}, "geo": null, "status": 0, "userType": 0, "created_at": "Fri Sep 04 19:06:21 +0800 2015", "mlevel": 0, "comments_count": 6, "url_objects": [{"url_ori": "Kate spade", "object": {"act_status": "00", "containerid": "100808f4c5a010cd922245a794ed431ae1ecf6", "object": {"target_url": "http://weibo.cn/pages/100808f4c5a010cd922245a794ed431ae1ecf6", "display_name": "Kate spade", "mobile": {"url": {"status": "1", "scheme": "sinaweibo://pageinfo?pageid=100808f4c5a010cd922245a794ed431ae1ecf6&extparam=Kate+spade", "name": "Kate spade"}, "page_id": "100808f4c5a010cd922245a794ed431ae1ecf6", "card": {"status": "0", "scheme": "sinaweibo://pageinfo?pageid=100808f4c5a010cd922245a794ed431ae1ecf6&extparam=Kate+spade", "pic": "http://u1.sinaimg.cn/upload/2013/12/10/topic_page_2x.png", "contents": ["#Kate spade#"]}}, "short_url": "http://t.cn/zYVOYHM", "image": {"url": "http://u1.sinaimg.cn/upload/2013/12/10/topic_page_2x.png", "width": "", "height": ""}, "object_type": "topic", "summary": "", "url": "http://weibo.cn/pages/100808f4c5a010cd922245a794ed431ae1ecf6", "biz": {"containerid": "100808f4c5a010cd922245a794ed431ae1ecf6", "biz_id": "100808"}, "id": "1022:100808f4c5a010cd922245a794ed431ae1ecf6"}, "timestamp": 1446147570689, "object_type": "topic", "object_domain_id": "1022", "uuid": 3543520345330531, "object_id": "1022:100808f4c5a010cd922245a794ed431ae1ecf6", "safe_status": 1, "last_modified": "Tue Dec 17 23:30:44 CST 2013", "activate_status": "0", "show_status": "10"}, "object_id": "1022:100808f4c5a010cd922245a794ed431ae1ecf6", "card_info_un_integrity": false, "like_count": 51, "asso_like_count": 0, "follower_count": 20}]}