{"reposts_count": 2, "biz_feature": 4294967300, "truncated": false, "text": "\u3010\u63a8\u8350\u3011\u6211\u53c8\u51fa\u73b0\u5566~\u521a\u597d\u770b\u5230\u4e86kate spade\u7684\u5305\u5305\u6709\u4e00\u4e2a\u6298\u6263\u6240\u4ee5\u6765\u63a8\u8350\u5566\uff01\u611f\u89c9\u5f88\u9002\u5408\u8349\u8393\u6b3e\u7684\u5c0f\u751c\u54e6~\u6839\u636e\u5317\u7f8e\u7701\u94b1\u5feb\u62a5\u7684\u5fae\u535a\uff1ahttp://t.cn/RyAMulQ\u73b0\u5728\u662f\u516b\u6298\u65e0\u7a0e", "visible": {"type": 0, "list_id": 0}, "in_reply_to_status_id": "", "relation": null, "bmiddle_pic": "http://ww4.sinaimg.cn/bmiddle/0062PBRtjw1evqbwoiiooj30c80g80tl.jpg", "original_pic": "http://ww4.sinaimg.cn/large/0062PBRtjw1evqbwoiiooj30c80g80tl.jpg", "rid": "17_0_0_618401262581892195", "id": 3883334419242347, "category": 31, "thumbnail_pic": "http://ww4.sinaimg.cn/thumbnail/0062PBRtjw1evqbwoiiooj30c80g80tl.jpg", "mid": "3883334419242347", "source": "<a href=\"http://weibo.com/\" rel=\"nofollow\">\u6295\u7a3f\u770b\u7f6e\u9876iPhone 5s</a>", "attitudes_count": 5, "in_reply_to_screen_name": "", "in_reply_to_user_id": "", "base62_id": "CyXUlCMm7", "annotations": [{"client_mblogid": "iPhone-2DE0C502-D9A0-4BA6-8FDD-6669FF992E1F"}, {"mapi_request": true}], "darwin_tags": [], "favorited": false, "pic_ids": ["0062PBRtjw1evqbwoiiooj30c80g80tl", "0062PBRtjw1evqbwp2oqkj30c80c1my5", "0062PBRtjw1evqbwpc5t8j30c80fqjro"], "source_allowclick": 0, "idstr": "3883334419242347", "source_type": 2, "user": {"bi_followers_count": 18, "domain": "shuogeiloniang", "avatar_large": "http://tp4.sinaimg.cn/5538649935/180/5728051516/0", "verified_source": "", "ptype": 0, "ulevel": 0, "block_word": 0, "cover_image_phone": "http://ww4.sinaimg.cn/crop.0.0.640.640.640/6ce2240djw1e8iktk4ohij20hs0hsmz6.jpg", "star": 0, "id": 5538649935, "verified_reason_url": "", "urank": 15, "city": "1", "verified": false, "extend": {"mbprivilege": "0000000000000000000000000000000000000000000000000000000000400208", "privacy": {"mobile": 1}}, "credit_score": 80, "has_ability_tag": 1, "block_app": 1, "follow_me": false, "verified_reason": "", "followers_count": 18412, "location": "\u5317\u4eac \u4e1c\u57ce\u533a", "badge_top": "", "verified_trade": "", "mbtype": 13, "type": 1, "verified_source_url": "", "profile_url": "shuogeiloniang", "province": "11", "avatar_hd": "http://ww2.sinaimg.cn/crop.0.0.1080.1080.1024/0062PBRtjw8esntsvimvkj30u00u03zl.jpg", "statuses_count": 12523, "description": "\u63a5\u53d7\u79c1\u4fe1 \u539f\u521b/\u8bc4\u8bba\u827e\u7279\u6295\u7a3f \u8f6c\u53d1\u827e\u7279\u770b\u4e0d\u5230\u54e6\u3002\u5c82\u80fd\u5c3d\u5982\u4eba\u610f\uff0c\u4f46\u6c42\u65e0\u6127\u4e8e\u5fc3\u3002\u6295\u7a3f\u524d\u8bf7\u4ed4\u7ec6\u67e5\u770b\u7f6e\u9876\u5fae\u535a\u5185\u5bb9\u548c\u8bc4\u8bba\u3002", "friends_count": 44, "online_status": 0, "mbrank": 3, "idstr": "5538649935", "profile_image_url": "http://tp4.sinaimg.cn/5538649935/50/5728051516/0", "allow_all_act_msg": false, "following": false, "badge": {"bind_taobao": 0, "hongbao_2014": 0, "gongyi_level": 0, "dailv": 0, "gongyi": 0, "travel2013": 0, "anniversary": 0, "shuang11_2015": 0, "taobao": 0, "uc_domain": 0, "enterprise": 0, "suishoupai_2014": 0, "zongyiji": 0}, "allow_all_comment": true, "geo_enabled": true, "class": 1, "name": "\u8bf4\u7ed9lo\u5a18", "lang": "zh-cn", "weihao": "", "remark": "", "favourites_count": 4, "screen_name": "\u8bf4\u7ed9lo\u5a18", "level": 1, "url": "", "gender": "f", "created_at": "Fri Feb 27 21:33:18 +0800 2015", "verified_type": -1, "cover_image": "http://ww1.sinaimg.cn/crop.0.0.920.300/0062PBRtgw1etzqtn3rlvj30pk08cq8q.jpg", "pagefriends_count": 0, "user_ability": 0}, "geo": null, "status": 0, "userType": 0, "created_at": "Fri Sep 04 12:55:37 +0800 2015", "mlevel": 0, "comments_count": 6, "url_objects": [{"info": {"description": "", "title": "", "url_short": "http://t.cn/RyAMulQ", "last_modified": 1441205668, "url_long": "http://cn.dealmoon.com/20-Off-Kate-Spade-Handbags-Lord-Taylor/457613.html?s=meibao&utm_source=weibo&utm_medium=meibao&utm_campaign=dealmoon", "result": true, "transcode": 2, "type": 0}, "url_ori": "http://t.cn/RyAMulQ", "card_info_un_integrity": false, "like_count": 0, "asso_like_count": 0, "follower_count": 0}]}