{"reposts_count": 0, "biz_feature": 4294967300, "truncated": false, "text": "#kate spade#\u00a5455+\u56fd\u5185\u8fd0\u8d39\u5230\u624b", "visible": {"type": 0, "list_id": 0}, "in_reply_to_status_id": "", "relation": null, "bmiddle_pic": "http://ww4.sinaimg.cn/bmiddle/7cb0c757gw1ewa6v2ijobj20hs0elt9q.jpg", "original_pic": "http://ww4.sinaimg.cn/large/7cb0c757gw1ewa6v2ijobj20hs0elt9q.jpg", "rid": "36_0_0_2789455321734426920", "id": 3889561018997613, "category": 31, "thumbnail_pic": "http://ww4.sinaimg.cn/thumbnail/7cb0c757gw1ewa6v2ijobj20hs0elt9q.jpg", "mid": "3889561018997613", "source": "<a href=\"http://app.weibo.com/t/feed/3o33sO\" rel=\"nofollow\">iPhone 6</a>", "attitudes_count": 0, "in_reply_to_screen_name": "", "in_reply_to_user_id": "", "base62_id": "CBzTfBKGN", "annotations": [{"client_mblogid": "iPhone-17FD9147-2891-4344-BE85-EB9DCF9976A0"}, {"mapi_request": true}], "darwin_tags": [], "favorited": false, "pic_ids": ["7cb0c757gw1ewa6v2ijobj20hs0elt9q", "7cb0c757gw1ewa6v0dzkyj20hs0jrwhd", "7cb0c757gw1ewa6v2wadyj20hs0ffdgp", "7cb0c757gw1ewa6v39nohj20hs0lqq5d", "7cb0c757gw1ewa6v4pwfjj20hs0fewfp", "7cb0c757gw1ewa6v49xzwj20hs0jd40g", "7cb0c757gw1ewa6v58gocj20hs0ewdgf", "7cb0c757gw1ewa6v5o0cnj20hs0gtjsi", "7cb0c757gw1ewa6v60ebfj20hs0g4gmc"], "source_allowclick": 0, "idstr": "3889561018997613", "source_type": 1, "user": {"bi_followers_count": 9, "domain": "", "avatar_large": "http://tp4.sinaimg.cn/2091960151/180/5738917190/0", "verified_source": "", "ptype": 0, "ulevel": 0, "block_word": 0, "star": 0, "id": 2091960151, "verified_reason_url": "", "urank": 19, "city": "1000", "verified": false, "extend": {"mbprivilege": "0000000000000000000000000000000000000000000000000000000000c00208", "privacy": {"mobile": 0}}, "credit_score": 80, "has_ability_tag": 0, "block_app": 1, "follow_me": false, "verified_reason": "", "followers_count": 619, "location": "\u5176\u4ed6", "badge_top": "", "verified_trade": "", "mbtype": 11, "type": 1, "verified_source_url": "", "profile_url": "53642010", "province": "100", "avatar_hd": "http://ww3.sinaimg.cn/crop.0.0.749.749.1024/7cb0c757jw8ewp7wabgmuj20ku0ktt9a.jpg", "statuses_count": 711, "description": "20-25\u5929\u5230\u56fd\u5185\u3002\u7f8e\u56fd\u5404\u5927\u724c\u5b50\u90fd\u80fd\u4ee3\u8d2d\uff0c\u7279\u522b\u662f\u6298\u6263\u597d\u7684\u90fd\u4f1a\u53d1\u51fa\u6765\u5206\u4eab\u3002\u79c1\u4fe1\u6ca1\u56de\u590d\u53ef\u4ee5\u52a0\ud83d\ude01\u5fae\u4fe113506036811\u4f1a\u53ca\u65f6\u66f4\u65b0\u54e6", "friends_count": 147, "online_status": 0, "mbrank": 1, "idstr": "2091960151", "profile_image_url": "http://tp4.sinaimg.cn/2091960151/50/5738917190/0", "allow_all_act_msg": false, "badge": {"bind_taobao": 0, "hongbao_2014": 0, "gongyi_level": 0, "dailv": 0, "gongyi": 0, "travel2013": 0, "anniversary": 0, "shuang11_2015": 0, "taobao": 0, "uc_domain": 0, "enterprise": 0, "suishoupai_2014": 0, "zongyiji": 0}, "allow_all_comment": true, "geo_enabled": true, "class": 1, "name": "\u5c0f\u8611\u83c7\u83c7\u7f8e\u56fd\u4ee3\u8d2d", "lang": "zh-cn", "weihao": "53642010", "remark": "", "favourites_count": 18, "screen_name": "\u5c0f\u8611\u83c7\u83c7\u7f8e\u56fd\u4ee3\u8d2d", "level": 6, "url": "", "gender": "f", "created_at": "Sun Apr 17 12:23:26 +0800 2011", "verified_type": 200, "following": false, "pagefriends_count": 0, "user_ability": 0}, "geo": null, "status": 0, "userType": 0, "created_at": "Mon Sep 21 17:17:54 +0800 2015", "mlevel": 0, "comments_count": 0, "url_objects": [{"url_ori": "kate spade", "object": {"act_status": "00", "containerid": "100808f50d476b34b7991f27edf2bd743e0268", "object": {"target_url": "http://weibo.cn/pages/100808f50d476b34b7991f27edf2bd743e0268", "display_name": "kate spade", "mobile": {"url": {"status": "1", "scheme": "sinaweibo://pageinfo?pageid=100808f50d476b34b7991f27edf2bd743e0268&extparam=kate+spade", "name": "kate spade"}, "page_id": "100808f50d476b34b7991f27edf2bd743e0268", "card": {"status": "0", "scheme": "sinaweibo://pageinfo?pageid=100808f50d476b34b7991f27edf2bd743e0268&extparam=kate+spade", "pic": "http://u1.sinaimg.cn/upload/2013/12/10/topic_page_2x.png", "contents": ["#kate spade#"]}}, "short_url": "http://t.cn/zYcVkYT", "image": {"url": "http://u1.sinaimg.cn/upload/2013/12/10/topic_page_2x.png", "width": "", "height": ""}, "object_type": "topic", "summary": "", "url": "http://weibo.cn/pages/100808f50d476b34b7991f27edf2bd743e0268", "biz": {"containerid": "100808f50d476b34b7991f27edf2bd743e0268", "biz_id": "100808"}, "id": "1022:100808f50d476b34b7991f27edf2bd743e0268"}, "timestamp": 1446147190945, "object_type": "topic", "object_domain_id": "1022", "uuid": 3543066504880219, "object_id": "1022:100808f50d476b34b7991f27edf2bd743e0268", "safe_status": 1, "last_modified": "Tue Dec 17 19:48:26 CST 2013", "activate_status": "0", "show_status": "10"}, "object_id": "1022:100808f50d476b34b7991f27edf2bd743e0268", "card_info_un_integrity": false, "like_count": 308, "asso_like_count": 0, "follower_count": 125}]}