{"reposts_count": 0, "biz_feature": 0, "truncated": false, "text": "#\u8d4f\u5473\u7f8e\u7269# kate spade 2waytote\u888b\uff0c\u9ed1\u8272\u725b\u76ae\uff0c\u7acb\u4f53\u683c\u7eb9\u7f1d\u7ebf\u975e\u5e38\u9971\u6ee1\uff0c\u63d0\u624b\u662f\u7a7f\u76ae\u9769\u94fe\u6761\u6b3e\u7684\u54e6\uff0c\u7cbe\u81f4\u88c5\u9970\u611f\u597d\uff0c27/33x27x10cm\uff0c\u957f\u80a9\u5e26115cm\uff0c97\u65b0\u5de6\u53f3\u7f8e\u54c1\uff0c\u57fa\u672c\u53ea\u6709\u753b\u5708\u5904\u5185\u91cc\u4e00\u70b9\u5c0f\u75d5\u8ff9\uff0c\u5176\u4ed6\u6ca1\u5565\u8981\u8bf4\u7684\uff0c\u6536\u7eb3\u888b\u5728\uff0c1800\u9886\u8d70\uff0c\u53c2\u8003\u539f\u4ef7\u8fd13\u5343\u3002\u597d\u770b\u53c8\u633a\u5b9e\u7528\u7684\u4e00\u53eatote\uff0c\u63a8\u8350~", "visible": {"type": 0, "list_id": 0}, "in_reply_to_status_id": "", "bmiddle_pic": "http://ww4.sinaimg.cn/bmiddle/c0acde58gw1ewi6nep68oj20hs0fdq4m.jpg", "original_pic": "http://ww4.sinaimg.cn/large/c0acde58gw1ewi6nep68oj20hs0fdq4m.jpg", "rid": "0_0_0_2789461480717138729", "id": 3892066763059163, "category": 31, "thumbnail_pic": "http://ww4.sinaimg.cn/thumbnail/c0acde58gw1ewi6nep68oj20hs0fdq4m.jpg", "mid": "3892066763059163", "source": "<a href=\"http://weibo.com/\" rel=\"nofollow\">\u5fae\u535a weibo.com</a>", "attitudes_count": 2, "in_reply_to_screen_name": "", "in_reply_to_user_id": "", "darwin_tags": [], "favorited": false, "pic_ids": ["c0acde58gw1ewi6nep68oj20hs0fdq4m", "c0acde58gw1ewi6nf4dquj20hs0m6wje", "c0acde58gw1ewi6nfyfdcj20hs0s878w"], "source_allowclick": 0, "idstr": "3892066763059163", "source_type": 1, "user": {"bi_followers_count": 1, "domain": "", "avatar_large": "http://tp1.sinaimg.cn/3232554584/180/5713168643/1", "verified_source": "", "ptype": 0, "ulevel": 0, "block_word": 0, "cover_image_phone": "http://ww3.sinaimg.cn/crop.0.0.640.640.640/6ce2240djw1e9oafaeu2vj20hs0hsn0f.jpg", "star": 0, "id": 3232554584, "verified_reason_url": "", "urank": 19, "city": "16", "verified": false, "extend": {"mbprivilege": "0000000000000000000000000000000000000000000000000000000000400208", "privacy": {"mobile": 1}}, "credit_score": 80, "has_ability_tag": 1, "block_app": 1, "follow_me": false, "verified_reason": "", "followers_count": 2676, "location": "\u6d77\u5916 \u5176\u4ed6", "verified_trade": "", "mbtype": 11, "badge_top": "", "verified_source_url": "", "profile_url": "u/3232554584", "province": "400", "avatar_hd": "http://ww3.sinaimg.cn/crop.36.12.108.108.1024/c0acde58jw1en4ol3av9fj2050050q39.jpg", "statuses_count": 2066, "description": "\u90fd\u90a3\u4e48\u719f\u4e86\uff0c\u8fd8\u4ecb\u7ecd\u4e2a\u5565\u3002", "friends_count": 44, "online_status": 0, "mbrank": 3, "idstr": "3232554584", "profile_image_url": "http://tp1.sinaimg.cn/3232554584/50/5713168643/1", "allow_all_act_msg": false, "allow_all_comment": false, "geo_enabled": true, "class": 1, "name": "\u8d4f\u5473\u7684\u94fa\u5b50", "lang": "zh-cn", "weihao": "", "favourites_count": 16, "screen_name": "\u8d4f\u5473\u7684\u94fa\u5b50", "url": "", "gender": "m", "created_at": "Thu Mar 21 23:29:38 +0800 2013", "verified_type": -1, "following": false, "pagefriends_count": 1, "user_ability": 0}, "geo": null, "userType": 0, "created_at": "Mon Sep 28 15:14:50 +0800 2015", "mlevel": 0, "comments_count": 0, "url_objects": [{"url_ori": "\u8d4f\u5473\u7f8e\u7269", "object": {"act_status": "00", "containerid": "10080805ad972a38d801f69a3f36e8ecf5c145", "object": {"category": "\u521b\u610f\u5f81\u96c6|9", "target_url": "http://huati.weibo.com/198130", "display_name": "\u8d4f\u5473\u7f8e\u7269", "presenter_status": "1", "mobile": {"url": {"status": "1", "scheme": "sinaweibo://pageinfo?pageid=10080805ad972a38d801f69a3f36e8ecf5c145&extparam=\u8d4f\u5473\u7f8e\u7269", "name": "\u8d4f\u5473\u7f8e\u7269"}, "page_id": "10080805ad972a38d801f69a3f36e8ecf5c145"}, "short_url": "http://t.cn/zYVuABs", "image": {"url": "http://ww1.sinaimg.cn/thumbnail/0062NRPGgw1eu2cwpugx5j30500503yn.jpg"}, "object_type": "topic", "create_at": "1370935157", "summary": "\u6c55\u5934\u767e\u683c\u54c1\u724c\u8bbe\u8ba1\u516c\u53f8\u4e13\u6ce8\u5404\u79cd\u98df\u54c1\u5305\u88c5\u8bbe\u8ba1\u3001\u54c1\u724c\u7b56\u5212\u3001LOGO\u8bbe\u8ba1\u3001VI\u8bbe\u8ba1\u7b49\u4e1a\u52a1\u3002\u6b22\u8fce\u524d\u6765\u54a8\u8be2\u6d3d\u8c08 \u66f4\u591a\u6848\u4f8b\u8bf7\u5230\u5b98\u7f51http://www.stbaige.com\n\u5982\u9700\u8981\u8bbe\u8ba1\u65f6\u8bf7\u4e0e\u6211\u8054\u7cfb:15875361105 QQ 417218781", "url": "http://huati.weibo.com/198130", "biz": {"containerid": "10080805ad972a38d801f69a3f36e8ecf5c145", "biz_id": "100808"}, "page_type": "1", "attribute": "1", "tid": "198130", "topic_tag": "\u7f8e\u7269,\u800c\u4e14\u521b\u610f", "id": "1022:10080805ad972a38d801f69a3f36e8ecf5c145", "location": "0-0"}, "timestamp": 1445678562727, "object_type": "topic", "object_domain_id": "1022", "uuid": 3543592659364763, "object_id": "1022:10080805ad972a38d801f69a3f36e8ecf5c145", "safe_status": 1, "last_modified": "Sat Oct 24 17:22:42 CST 2015", "activate_status": "0", "show_status": "10"}, "object_id": "1022:10080805ad972a38d801f69a3f36e8ecf5c145", "card_info_un_integrity": false, "like_count": 363, "asso_like_count": 0, "follower_count": 106}]}