{"reposts_count": 0, "biz_feature": 0, "truncated": false, "text": "http://t.cn/RzAJWdt kate spade NEW YORK Cobble Hill Small Devin \u5973\u6b3e\u771f\u76ae\u5355\u80a9\u5305 $197.95,\u6b3e\u5f0f\u7ecf\u5178\uff0c\u51fa\u8857\u5229\u5668\u3002\u91c7\u7528\u771f\u76ae\u6750\u8d28\u5236\u4f5c\uff0c\u5305\u8eab\u5706\u6da6\uff0c\u7ffb\u76d6\u6b3e\u5f0f\uff0c\u65b9\u4fbf\u5b89\u5168\u3002\u5185\u91cc\u5e26\u6709\u5c0f\u9694\u5c42\uff0c\u53ef\u4ee5\u5b58\u653e\u5c0f\u4ef6\u7269\u54c1\u3002 http://t.cn/RzwEFWW", "visible": {"type": 0, "list_id": 0}, "in_reply_to_status_id": "", "relation": null, "bmiddle_pic": "http://ww3.sinaimg.cn/bmiddle/005Z9rW5jw1evhizqan9kj30bt0dwaat.jpg", "original_pic": "http://ww3.sinaimg.cn/large/005Z9rW5jw1evhizqan9kj30bt0dwaat.jpg", "rid": "11_0_0_2666480495258854749", "id": 3895929058674213, "category": 31, "thumbnail_pic": "http://ww3.sinaimg.cn/thumbnail/005Z9rW5jw1evhizqan9kj30bt0dwaat.jpg", "mid": "3895929058674213", "source": "<a href=\"http://app.weibo.com/t/feed/6L4983\" rel=\"nofollow\">\u6d77\u6dd8\u503c\u5566</a>", "attitudes_count": 0, "in_reply_to_screen_name": "", "in_reply_to_user_id": "", "base62_id": "CEfyhAoyF", "darwin_tags": [], "favorited": false, "pic_ids": ["005Z9rW5jw1evhizqan9kj30bt0dwaat", "005Z9rW5jw1evhj4xu99xj308p0dwaad", "005Z9rW5jw1evhja63t2ej30510dwq33", "005Z9rW5jw1evhjfbvb3dj30dw06s3z3", "005Z9rW5jw1evhjklvlbvj30dw06mt98", "005Z9rW5jw1evhjpqp83kj30620dwdfy"], "source_allowclick": 0, "idstr": "3895929058674213", "source_type": 1, "user": {"bi_followers_count": 46, "domain": "amazonusdiscount", "avatar_large": "http://tp3.sinaimg.cn/3224438662/180/5658150267/0", "verified_source": "", "ptype": 0, "ulevel": 0, "block_word": 0, "star": 0, "id": 3224438662, "verified_reason_url": "", "urank": 29, "city": "1", "verified": false, "extend": {"mbprivilege": "0000000000000000000000000000000000000000000000000000000000400208", "privacy": {"mobile": 0}}, "credit_score": 80, "has_ability_tag": 1, "block_app": 1, "follow_me": false, "verified_reason": "", "followers_count": 160936, "location": "\u6d77\u5916 \u7f8e\u56fd", "badge_top": "", "verified_trade": "", "mbtype": 12, "type": 1, "verified_source_url": "", "profile_url": "amazonusdiscount", "province": "400", "avatar_hd": "http://tp3.sinaimg.cn/3224438662/180/5658150267/0", "statuses_count": 114976, "description": "\u5feb\u901f\u6d77\u6dd8\u653b\u7565http://t.cn/8Fd2UnD\u63a8\u8350\u8f6c\u8fd0\u516c\u53f8\uff1aQQ-EX\uff1ahttp://t.cn/zQfRuEo\uff1b\u5510\u4e09\u85cf\u8f6c\u8fd0\uff1ahttp://t.cn/zQfExVa\uff1b", "friends_count": 55, "online_status": 0, "mbrank": 6, "idstr": "3224438662", "profile_image_url": "http://tp3.sinaimg.cn/3224438662/50/5658150267/0", "allow_all_act_msg": true, "following": false, "badge": {"bind_taobao": 1, "hongbao_2014": 1, "gongyi_level": 1, "dailv": 0, "gongyi": 0, "travel2013": 0, "anniversary": 0, "shuang11_2015": 0, "taobao": 1, "uc_domain": 0, "enterprise": 0, "suishoupai_2014": 0, "zongyiji": 0}, "allow_all_comment": true, "geo_enabled": false, "class": 1, "name": "Amazon\u7f8e\u56fd\u4e9a\u9a6c\u900a\u7f8e\u6dd8\u6d77\u6dd8\u60e0", "lang": "zh-cn", "weihao": "", "remark": "", "favourites_count": 1, "screen_name": "Amazon\u7f8e\u56fd\u4e9a\u9a6c\u900a\u7f8e\u6dd8\u6d77\u6dd8\u60e0", "level": 7, "url": "http://blog.sina.com.cn/amazonusdiscount", "gender": "f", "created_at": "Wed Mar 13 19:56:21 +0800 2013", "verified_type": 220, "cover_image": "http://ww1.sinaimg.cn/crop.0.103.980.300/c0310786jw1e2smtse6udj.jpg", "pagefriends_count": 0, "user_ability": 0}, "geo": null, "status": 0, "userType": 0, "created_at": "Fri Oct 09 07:02:13 +0800 2015", "mlevel": 0, "comments_count": 0, "url_objects": [{"info": {"description": "", "title": "", "url_short": "http://t.cn/RzAJWdt", "last_modified": 1416526326, "url_long": "http://htzla.com/go/24126?tag=mov1-20&asin=B00KGZ831W", "result": true, "transcode": 0, "type": 0}, "url_ori": "http://t.cn/RzAJWdt", "card_info_un_integrity": false, "like_count": 0, "asso_like_count": 0, "follower_count": 0}, {"info": {"description": "", "title": "", "url_short": "http://t.cn/RzwEFWW", "last_modified": 1416480358, "url_long": "http://htzla.com/z.php?p=24126&a=B00KGZ831W&c=us", "result": true, "transcode": 0, "type": 0}, "url_ori": "http://t.cn/RzwEFWW", "card_info_un_integrity": false, "like_count": 0, "asso_like_count": 0, "follower_count": 0}]}