{"reposts_count": 0, "biz_feature": 0, "truncated": false, "text": "[\u7231\u4f60]", "visible": {"type": 0, "list_id": 0}, "in_reply_to_status_id": "", "id": 3888051065091307, "source_allowclick": 0, "mid": "3888051065091307", "source": "<a href=\"http://app.weibo.com/t/feed/1oul9z\" rel=\"nofollow\">iPad mini</a>", "attitudes_count": 0, "in_reply_to_screen_name": "", "in_reply_to_user_id": "", "annotations": [{"mapi_request": true}], "darwin_tags": [], "favorited": false, "pic_ids": [], "retweeted_status": {"reposts_count": 4, "biz_feature": 4294967298, "truncated": false, "text": "Show\u2503@\u5b59\u83f2\u83f2LZ at Michael Kors S/S 2016 \u7ebd\u7ea6\u5f53\u65e5\u7b2c\u4e00\u573a", "visible": {"type": 0, "list_id": 0}, "in_reply_to_status_id": "", "bmiddle_pic": "http://ww4.sinaimg.cn/bmiddle/d445a01djw1ew5cgez6wyj20hs0qogna.jpg", "original_pic": "http://ww4.sinaimg.cn/large/d445a01djw1ew5cgez6wyj20hs0qogna.jpg", "id": 3888041418234219, "thumbnail_pic": "http://ww4.sinaimg.cn/thumbnail/d445a01djw1ew5cgez6wyj20hs0qogna.jpg", "mid": "3888041418234219", "source": "<a href=\"http://app.weibo.com/t/feed/1oul9z\" rel=\"nofollow\">iPad mini</a>", "attitudes_count": 29, "in_reply_to_screen_name": "", "in_reply_to_user_id": "", "annotations": [{"client_mblogid": "iPhone-B7658536-E293-4C3F-AB63-7BA6C16C8F8A", "shooting": 1}, {"mapi_request": true}], "darwin_tags": [], "favorited": false, "pic_ids": ["d445a01djw1ew5cgez6wyj20hs0qogna", "d445a01djw1ew5cgg1f2rj20hs0qrmym", "d445a01djw1ew5cghnnpnj20hs0qowg0", "d445a01djw1ew5cgjmka0j20hs0qot9v", "d445a01djw1ew5cgm11q0j20hs0qo3zu", "d445a01djw1ew5cgnqhu1j20hs0qoq4p"], "source_allowclick": 0, "idstr": "3888041418234219", "source_type": 1, "user": {"bi_followers_count": 30, "domain": "motesunfeifei", "avatar_large": "http://tp2.sinaimg.cn/3561332765/180/5738237946/1", "verified_source": "", "ptype": 0, "ulevel": 0, "block_word": 0, "star": 0, "id": 3561332765, "verified_reason_url": "", "urank": 20, "city": "1000", "verified": false, "extend": {"mbprivilege": "0000000000000000000000000000000000000000000000000000000000400208", "privacy": {"mobile": 1}}, "credit_score": 80, "has_ability_tag": 1, "block_app": 1, "follow_me": false, "verified_reason": "", "followers_count": 3174, "location": "\u5317\u4eac", "badge_top": "", "verified_trade": "", "mbtype": 12, "type": 1, "verified_source_url": "", "profile_url": "motesunfeifei", "province": "11", "avatar_hd": "http://ww4.sinaimg.cn/crop.0.117.1200.1200.1024/d445a01djw8ewg4p5pbicj20xc13vak5.jpg", "statuses_count": 1481, "description": "\u201c\u6a21\u7279\u5b59\u83f2\u83f2\u201d\u8d34\u5427 http://t.cn/zHDHPGT\uff1bQ\u7fa4 122628771", "friends_count": 41, "online_status": 0, "mbrank": 3, "idstr": "3561332765", "profile_image_url": "http://tp2.sinaimg.cn/3561332765/50/5738237946/1", "allow_all_act_msg": false, "badge": {"bind_taobao": 0, "hongbao_2014": 0, "gongyi_level": 0, "dailv": 0, "gongyi": 0, "travel2013": 1, "anniversary": 0, "shuang11_2015": 0, "taobao": 0, "uc_domain": 0, "enterprise": 0, "suishoupai_2014": 0, "zongyiji": 0}, "allow_all_comment": true, "geo_enabled": true, "class": 1, "name": "Fei-Fei\u767e\u5ea6\u8d34\u5427", "lang": "zh-cn", "weihao": "", "remark": "", "favourites_count": 0, "screen_name": "Fei-Fei\u767e\u5ea6\u8d34\u5427", "level": 1, "url": "", "gender": "m", "created_at": "Thu Jun 27 08:56:26 +0800 2013", "verified_type": -1, "following": false, "pagefriends_count": 0, "user_ability": 0}, "geo": null, "userType": 0, "created_at": "Thu Sep 17 12:39:32 +0800 2015", "mlevel": 0, "comments_count": 3}, "idstr": "3888051065091307", "source_type": 1, "user": {"bi_followers_count": 2, "domain": "", "avatar_large": "http://tp4.sinaimg.cn/5299824483/180/5721022389/0", "verified_source": "", "ptype": 0, "ulevel": 0, "block_word": 0, "cover_image_phone": "http://ww1.sinaimg.cn/crop.0.0.640.640.640/6cf8d7ebjw1ehfr4xa8psj20hs0hsgpg.jpg", "star": 0, "id": 5299824483, "verified_reason_url": "", "urank": 20, "city": "1000", "verified": false, "extend": {"mbprivilege": "0000000000000000000000000000000000000000000000000000000000000000", "privacy": {"mobile": 0}}, "credit_score": 80, "has_ability_tag": 0, "block_app": 0, "follow_me": true, "verified_reason": "", "followers_count": 169, "location": "\u5317\u4eac", "badge_top": "", "verified_trade": "", "mbtype": 0, "type": 1, "verified_source_url": "", "profile_url": "u/5299824483", "province": "11", "avatar_hd": "http://ww2.sinaimg.cn/crop.0.0.640.640.1024/005MFws3jw8eq1rt294izj30hs0hsdg9.jpg", "statuses_count": 2599, "description": "", "friends_count": 1277, "online_status": 0, "mbrank": 0, "idstr": "5299824483", "profile_image_url": "http://tp4.sinaimg.cn/5299824483/50/5721022389/0", "allow_all_act_msg": false, "badge": {"bind_taobao": 0, "hongbao_2014": 0, "gongyi_level": 0, "dailv": 0, "gongyi": 0, "travel2013": 0, "anniversary": 0, "shuang11_2015": 0, "taobao": 0, "uc_domain": 0, "enterprise": 0, "suishoupai_2014": 0, "zongyiji": 1}, "allow_all_comment": true, "geo_enabled": true, "class": 1, "name": "\u4e09\u9646\u9646", "lang": "zh-cn", "weihao": "", "remark": "", "favourites_count": 1343, "screen_name": "\u4e09\u9646\u9646", "level": 1, "url": "", "gender": "f", "created_at": "Thu Sep 18 16:31:23 +0800 2014", "verified_type": -1, "following": false, "pagefriends_count": 4, "user_ability": 0}, "geo": null, "userType": 0, "created_at": "Thu Sep 17 13:17:53 +0800 2015", "mlevel": 0, "comments_count": 0}